LICENSE
README.md
setup.cfg
setup.py
pyiikocloudapi/__init__.py
pyiikocloudapi/api.py
pyiikocloudapi/decorators.py
pyiikocloudapi/exception.py
pyiikocloudapi/models.py
pyiikocloudapi.egg-info/PKG-INFO
pyiikocloudapi.egg-info/SOURCES.txt
pyiikocloudapi.egg-info/dependency_links.txt
pyiikocloudapi.egg-info/not-zip-safe
pyiikocloudapi.egg-info/requires.txt
pyiikocloudapi.egg-info/top_level.txt