Metadata-Version: 2.1
Name: pyiikocloudapi
Version: 0.0.28
Summary: Python services for convenient work with iiko Transport / iiko cloud api
Home-page: UNKNOWN
Author: kebrick
Author-email: ruban.kebr@gmail.com
License: MIT
Project-URL: Source, https://github.com/kebrick/pyiikocloupapi
Project-URL: Tracker, https://github.com/kebrick/pyiikocloupapi/issues
Platform: UNKNOWN
Requires-Python: >=3.7
License-File: LICENSE
